odoo/addons/web_tree_image_tooltip/README.rst
odoo/addons/web_tree_image_tooltip/__init__.py
odoo/addons/web_tree_image_tooltip/__manifest__.py
odoo/addons/web_tree_image_tooltip/i18n/it.po
odoo/addons/web_tree_image_tooltip/i18n/web_tree_image.pot
odoo/addons/web_tree_image_tooltip/i18n/web_tree_image_tooltip.pot
odoo/addons/web_tree_image_tooltip/i18n/zh_CN.po
odoo/addons/web_tree_image_tooltip/readme/CONFIGURE.rst
odoo/addons/web_tree_image_tooltip/readme/CONTRIBUTORS.rst
odoo/addons/web_tree_image_tooltip/readme/CREDITS.rst
odoo/addons/web_tree_image_tooltip/readme/DESCRIPTION.rst
odoo/addons/web_tree_image_tooltip/readme/USAGE.rst
odoo/addons/web_tree_image_tooltip/static/description/icon.png
odoo/addons/web_tree_image_tooltip/static/description/index.html
odoo/addons/web_tree_image_tooltip/static/src/js/tooltip.js
odoo/addons/web_tree_image_tooltip/static/src/scss/common.scss
odoo/addons/web_tree_image_tooltip/view/assets.xml
odoo14_addon_web_tree_image_tooltip-14.0.1.0.1.dev4.dist-info/METADATA
odoo14_addon_web_tree_image_tooltip-14.0.1.0.1.dev4.dist-info/WHEEL
odoo14_addon_web_tree_image_tooltip-14.0.1.0.1.dev4.dist-info/top_level.txt
odoo14_addon_web_tree_image_tooltip-14.0.1.0.1.dev4.dist-info/RECORD
